OligoSeeker/__init__.py
OligoSeeker/_modidx.py
OligoSeeker/cli.py
OligoSeeker/core.py
OligoSeeker/dna_utils.py
OligoSeeker/fastq.py
OligoSeeker/merge.py
OligoSeeker/output.py
OligoSeeker/pipeline.py
oligoseeker-0.0.6.dist-info/LICENSE
oligoseeker-0.0.6.dist-info/METADATA
oligoseeker-0.0.6.dist-info/WHEEL
oligoseeker-0.0.6.dist-info/entry_points.txt
oligoseeker-0.0.6.dist-info/top_level.txt
oligoseeker-0.0.6.dist-info/RECORD
