Metadata-Version: 2.1
Name: oligoseeker
Version: 0.0.6
Summary: A Python tool for processing paired FASTQ files to efficiently count oligo codons.
Home-page: https://github.com/mtinti/OligoSeeker
Author: mtinti
Author-email: michele.tinti@gmail.com
License: Apache Software License 2.0
Keywords: nbdev jupyter notebook python
Classifier: Development Status :: 4 - Beta
Classifier: Intended Audience :: Developers
Classifier: Natural Language :: English
Classifier: Programming Language :: Python :: 3.7
Classifier: Programming Language :: Python :: 3.8
Classifier: Programming Language :: Python :: 3.9
Classifier: Programming Language :: Python :: 3.10
Classifier: Programming Language :: Python :: 3.11
Classifier: Programming Language :: Python :: 3.12
Classifier: License :: OSI Approved :: Apache Software License
Requires-Python: >=3.7
License-File: LICENSE
Requires-Dist: biopython
Requires-Dist: fastcore
Requires-Dist: pandas
Requires-Dist: tqdm
Provides-Extra: dev
